bancointer/__init__.py
bancointer/bancointer.py
bancointer/banking.py
bancointer/deprecated.py
bancointer/util.py
bancointer/banking/__init__.py
bancointer/banking/extrato/__init__.py
bancointer/banking/extrato/consulta_extrato.py
bancointer/banking/extrato/consulta_extrato_pdf.py
bancointer/banking/models/__init__.py
bancointer/banking/models/aut_bank_erro.py
bancointer/banking/models/autbank_dados_conta.py
bancointer/banking/models/dados_pagamento.py
bancointer/banking/models/dados_pagamento_darf.py
bancointer/banking/models/destinatario_pagamento_pix.py
bancointer/banking/models/instituicao_financeira.py
bancointer/banking/models/requisicao_pagamento.py
bancointer/banking/models/requisicao_pagamento_darf.py
bancointer/banking/models/requisicao_pagamento_pix.py
bancointer/banking/models/resposta_busca_pagamento.py
bancointer/banking/models/resposta_busca_pagamento_darf.py
bancointer/banking/models/resposta_consulta_pagamento_pix.py
bancointer/banking/models/resposta_consultar_extrato.py
bancointer/banking/models/resposta_consultar_saldo.py
bancointer/banking/models/resposta_requisicao_pagamento.py
bancointer/banking/models/resposta_requisicao_pagamento_darf.py
bancointer/banking/models/resposta_requisicao_pagamento_pix.py
bancointer/banking/models/status_pagamento.py
bancointer/banking/models/status_transaco_pix.py
bancointer/banking/models/tipo_conta.py
bancointer/banking/models/tipo_destinatario_pagamento_pix.py
bancointer/banking/models/tipo_operacao.py
bancointer/banking/models/tipo_retorno.py
bancointer/banking/models/tipo_retorno_pagamento_pix.py
bancointer/banking/models/tipo_transacao.py
bancointer/banking/models/transacao_pix.py
bancointer/banking/models/transacao_simples.py
bancointer/banking/pagamento/__init__.py
bancointer/banking/pagamento/busca_pagamento.py
bancointer/banking/pagamento/busca_pagamento_darf.py
bancointer/banking/pagamento/cancela_agendamento_pagamento.py
bancointer/banking/pagamento/inclui_pagamento_codbar.py
bancointer_python-0.16.dist-info/LICENSE
bancointer_python-0.16.dist-info/METADATA
bancointer_python-0.16.dist-info/WHEEL
bancointer_python-0.16.dist-info/top_level.txt
bancointer_python-0.16.dist-info/RECORD
