Metadata-Version: 2.2
Name: bancointer-python
Version: 0.16
Summary: Emita boletos bancários utilizando a API do Banco Inter PJ.
Author-email: "Renato P. Eduardo Jr" <renatojdev@outlook.com>
License: MIT License
Project-URL: homepage, https://github.com/renatojdev/bancointer-python
Project-URL: repository, https://github.com/renatojdev/bancointer-python
Project-URL: documentation, https://github.com/renatojdev/bancointer-python/blob/main/README.md
Platform: Linux
Platform: Windows
License-File: LICENSE
Requires-Dist: requests
Requires-Dist: certifi
Provides-Extra: dev
Requires-Dist: python-decouple; extra == "dev"
Requires-Dist: requests-mock; extra == "dev"
Requires-Dist: black; extra == "dev"
Requires-Dist: setuptools; extra == "dev"
Requires-Dist: wheel; extra == "dev"
Requires-Dist: twine; extra == "dev"
